{
  "$schema": "https://developer.microsoft.com/json-schemas/fabric/item/report/definition/visualContainer/2.5.0/schema.json",
  "name": "7006b3060694a314197d",
  "position": {
    "x": 651.11662531017362,
    "y": 64.5822994210091,
    "z": 7000,
    "height": 655.35153019023983,
    "width": 619.35483870967744,
    "tabOrder": 7000
  },
  "visual": {
    "visualType": "tableEx",
    "query": {
      "queryState": {
        "Values": {
          "projections": [
            {
              "field": {
                "Column": {
                  "Expression": {
                    "SourceRef": {
                      "Entity": "DIM_Locations"
                    }
                  },
                  "Property": "State Name"
                }
              },
              "queryRef": "DIM_Locations.State Name",
              "nativeQueryRef": "State Name"
            },
            {
              "field": {
                "Column": {
                  "Expression": {
                    "SourceRef": {
                      "Entity": "DIM_Locations"
                    }
                  },
                  "Property": "County"
                }
              },
              "queryRef": "DIM_Locations.County",
              "nativeQueryRef": "County"
            },
            {
              "field": {
                "Measure": {
                  "Expression": {
                    "SourceRef": {
                      "Entity": "_Measures"
                    }
                  },
                  "Property": "Sales Opportunity"
                }
              },
              "queryRef": "_Measures.Sales Opportunity",
              "nativeQueryRef": "Sales Opportunity"
            },
            {
              "field": {
                "Measure": {
                  "Expression": {
                    "SourceRef": {
                      "Entity": "_Measures"
                    }
                  },
                  "Property": "Total Sales"
                }
              },
              "queryRef": "_Measures.Total Sales",
              "nativeQueryRef": "Total Sales"
            },
            {
              "field": {
                "Measure": {
                  "Expression": {
                    "SourceRef": {
                      "Entity": "_Measures"
                    }
                  },
                  "Property": "Sales Density (100k)"
                }
              },
              "queryRef": "_Measures.Sales Density (100k)",
              "nativeQueryRef": "Sales Density (100k)"
            }
          ]
        }
      },
      "sortDefinition": {
        "sort": [
          {
            "field": {
              "Measure": {
                "Expression": {
                  "SourceRef": {
                    "Entity": "_Measures"
                  }
                },
                "Property": "Sales Opportunity"
              }
            },
            "direction": "Descending"
          }
        ]
      }
    },
    "objects": {
      "columnWidth": [
        {
          "properties": {
            "value": {
              "expr": {
                "Literal": {
                  "Value": "119.47146497447028D"
                }
              }
            }
          },
          "selector": {
            "metadata": "DIM_Locations.State Name"
          }
        },
        {
          "properties": {
            "value": {
              "expr": {
                "Literal": {
                  "Value": "103.23655609914515D"
                }
              }
            }
          },
          "selector": {
            "metadata": "DIM_Locations.County"
          }
        },
        {
          "properties": {
            "value": {
              "expr": {
                "Literal": {
                  "Value": "90.18446897551797D"
                }
              }
            }
          },
          "selector": {
            "metadata": "_Measures.Sales Opportunity"
          }
        },
        {
          "properties": {
            "value": {
              "expr": {
                "Literal": {
                  "Value": "101.42266335814723D"
                }
              }
            }
          },
          "selector": {
            "metadata": "_Measures.Total Sales"
          }
        },
        {
          "properties": {
            "value": {
              "expr": {
                "Literal": {
                  "Value": "89.71464019851118D"
                }
              }
            }
          },
          "selector": {
            "metadata": "_Measures.Sales Density (100k)"
          }
        }
      ],
      "columnFormatting": [
        {
          "properties": {
            "dataBars": {
              "positiveColor": {
                "solid": {
                  "color": {
                    "expr": {
                      "Literal": {
                        "Value": "'#1AAB40'"
                      }
                    }
                  }
                }
              },
              "negativeColor": {
                "solid": {
                  "color": {
                    "expr": {
                      "Literal": {
                        "Value": "'#D64554'"
                      }
                    }
                  }
                }
              },
              "axisColor": {
                "solid": {
                  "color": {
                    "expr": {
                      "Literal": {
                        "Value": "'foreground'"
                      }
                    }
                  }
                }
              },
              "reverseDirection": {
                "expr": {
                  "Literal": {
                    "Value": "false"
                  }
                }
              },
              "hideText": {
                "expr": {
                  "Literal": {
                    "Value": "false"
                  }
                }
              },
              "totalMatchingOption": {
                "expr": {
                  "Literal": {
                    "Value": "1L"
                  }
                }
              }
            }
          },
          "selector": {
            "metadata": "_Measures.Sales Opportunity"
          }
        }
      ]
    },
    "drillFilterOtherVisuals": true
  },
  "filterConfig": {
    "filters": [
      {
        "name": "f61a325b1c90d045e637",
        "ordinal": 0,
        "field": {
          "Column": {
            "Expression": {
              "SourceRef": {
                "Entity": "Calendar"
              }
            },
            "Property": "End of Month"
          }
        },
        "type": "Categorical",
        "howCreated": "User"
      },
      {
        "name": "04f579d7ae37e129de45",
        "ordinal": 1,
        "field": {
          "Column": {
            "Expression": {
              "SourceRef": {
                "Entity": "FCT_Sales"
              }
            },
            "Property": "Region"
          }
        },
        "type": "Categorical",
        "howCreated": "User"
      },
      {
        "name": "fbc652e130801a4a1226",
        "ordinal": 2,
        "field": {
          "Column": {
            "Expression": {
              "SourceRef": {
                "Entity": "_Select_Period"
              }
            },
            "Property": "Period"
          }
        },
        "type": "Categorical",
        "filter": {
          "Version": 2,
          "From": [
            {
              "Name": "_",
              "Entity": "_Select_Period",
              "Type": 0
            }
          ],
          "Where": [
            {
              "Condition": {
                "In": {
                  "Expressions": [
                    {
                      "Column": {
                        "Expression": {
                          "SourceRef": {
                            "Source": "_"
                          }
                        },
                        "Property": "Period"
                      }
                    }
                  ],
                  "Values": [
                    [
                      {
                        "Literal": {
                          "Value": "'Base'"
                        }
                      }
                    ],
                    [
                      {
                        "Literal": {
                          "Value": "'Rolling Avg (12Mo)'"
                        }
                      }
                    ]
                  ]
                }
              }
            }
          ]
        },
        "howCreated": "User"
      },
      {
        "name": "fc2004207c5abcdd2c1f",
        "ordinal": 3,
        "field": {
          "Measure": {
            "Expression": {
              "SourceRef": {
                "Entity": "_Measures"
              }
            },
            "Property": "Revenue"
          }
        },
        "type": "Advanced",
        "howCreated": "User"
      },
      {
        "name": "6b960db103a56ff88b04",
        "field": {
          "Column": {
            "Expression": {
              "SourceRef": {
                "Entity": "DIM_Locations"
              }
            },
            "Property": "State Name"
          }
        },
        "type": "Categorical"
      },
      {
        "name": "ab100b4de488e8df526c",
        "field": {
          "Column": {
            "Expression": {
              "SourceRef": {
                "Entity": "DIM_Locations"
              }
            },
            "Property": "County"
          }
        },
        "type": "Categorical"
      },
      {
        "name": "9c52ccee2cc7e088e66f",
        "field": {
          "Measure": {
            "Expression": {
              "SourceRef": {
                "Entity": "_Measures"
              }
            },
            "Property": "Sales Opportunity"
          }
        },
        "type": "Advanced"
      },
      {
        "name": "2ce237f38d1f59da2a6b",
        "field": {
          "Measure": {
            "Expression": {
              "SourceRef": {
                "Entity": "_Measures"
              }
            },
            "Property": "Total Sales"
          }
        },
        "type": "Advanced"
      },
      {
        "name": "b804cc7a043126c65da5",
        "field": {
          "Measure": {
            "Expression": {
              "SourceRef": {
                "Entity": "_Measures"
              }
            },
            "Property": "Sales Density (100k)"
          }
        },
        "type": "Advanced"
      }
    ],
    "filterSortOrder": "Custom"
  }
}