{
  "$schema": "https://developer.microsoft.com/json-schemas/fabric/item/report/definition/visualContainer/2.4.0/schema.json",
  "name": "078e7af4075501001b7b",
  "position": {
    "x": 650.90909090909088,
    "y": 400,
    "z": 11003,
    "height": 320,
    "width": 620,
    "tabOrder": 11004
  },
  "visual": {
    "visualType": "azureMap",
    "query": {
      "queryState": {
        "Size": {
          "projections": [
            {
              "field": {
                "Measure": {
                  "Expression": {
                    "SourceRef": {
                      "Entity": "_Measures"
                    }
                  },
                  "Property": "Shipping Miles"
                }
              },
              "queryRef": "_Measures.Shipping Miles",
              "nativeQueryRef": "Shipping Miles"
            }
          ]
        },
        "X": {
          "projections": [
            {
              "field": {
                "Column": {
                  "Expression": {
                    "SourceRef": {
                      "Entity": "DIM_Locations"
                    }
                  },
                  "Property": "lng"
                }
              },
              "queryRef": "DIM_Locations.lng",
              "nativeQueryRef": "lng"
            }
          ]
        },
        "Y": {
          "projections": [
            {
              "field": {
                "Column": {
                  "Expression": {
                    "SourceRef": {
                      "Entity": "DIM_Locations"
                    }
                  },
                  "Property": "lat"
                }
              },
              "queryRef": "DIM_Locations.lat",
              "nativeQueryRef": "lat"
            }
          ]
        }
      },
      "sortDefinition": {
        "isDefaultSort": true
      }
    },
    "objects": {
      "bubbleLayer": [
        {
          "properties": {
            "show": {
              "expr": {
                "Literal": {
                  "Value": "false"
                }
              }
            }
          }
        }
      ],
      "heatMapLayer": [
        {
          "properties": {
            "show": {
              "expr": {
                "Literal": {
                  "Value": "true"
                }
              }
            },
            "heatMapUseSize": {
              "expr": {
                "Literal": {
                  "Value": "false"
                }
              }
            },
            "heatMapRadius": {
              "expr": {
                "Literal": {
                  "Value": "10D"
                }
              }
            },
            "heatMapIntensity": {
              "expr": {
                "Literal": {
                  "Value": "2D"
                }
              }
            }
          }
        }
      ]
    },
    "drillFilterOtherVisuals": true
  },
  "filterConfig": {
    "filters": [
      {
        "name": "f724fe943b4720a5400b",
        "field": {
          "Column": {
            "Expression": {
              "SourceRef": {
                "Entity": "DIM_Locations"
              }
            },
            "Property": "lng"
          }
        },
        "type": "Advanced"
      },
      {
        "name": "6808ac7b86b16b072b9a",
        "field": {
          "Column": {
            "Expression": {
              "SourceRef": {
                "Entity": "DIM_Locations"
              }
            },
            "Property": "lat"
          }
        },
        "type": "Advanced"
      },
      {
        "name": "b242e18f4454490d720d",
        "field": {
          "Measure": {
            "Expression": {
              "SourceRef": {
                "Entity": "_Measures"
              }
            },
            "Property": "Shipping Miles"
          }
        },
        "type": "Advanced"
      }
    ]
  }
}