{
  "$schema": "https://developer.microsoft.com/json-schemas/fabric/item/report/definition/visualContainer/2.5.0/schema.json",
  "name": "d1043004780bf766da47",
  "position": {
    "x": 712.81795511221947,
    "y": 0,
    "z": 3000,
    "height": 54.763092269326684,
    "width": 494.66334164588528,
    "tabOrder": 3000
  },
  "visual": {
    "visualType": "textbox",
    "objects": {
      "general": [
        {
          "properties": {
            "paragraphs": [
              {
                "textRuns": [
                  {
                    "value": "Model Relationships",
                    "textStyle": {
                      "fontFamily": "Cambria Math",
                      "fontSize": "28pt",
                      "color": "#333333"
                    }
                  }
                ],
                "horizontalTextAlignment": "center"
              }
            ]
          }
        }
      ]
    },
    "visualContainerObjects": {
      "title": [
        {
          "properties": {
            "show": {
              "expr": {
                "Literal": {
                  "Value": "false"
                }
              }
            }
          }
        }
      ],
      "background": [
        {
          "properties": {
            "transparency": {
              "expr": {
                "Literal": {
                  "Value": "100D"
                }
              }
            }
          }
        }
      ]
    },
    "drillFilterOtherVisuals": true
  }
}